LICENSE
MANIFEST.in
README.md
requirements.txt
setup.cfg
setup.py
wis_downloader/__init__.py
wis_downloader/alos_dem.py
wis_downloader/downloader.py
wis_downloader/ncep_gfs.py
wis_downloader/wis_downloader.py
wis_downloader.egg-info/PKG-INFO
wis_downloader.egg-info/SOURCES.txt
wis_downloader.egg-info/dependency_links.txt
wis_downloader.egg-info/not-zip-safe
wis_downloader.egg-info/requires.txt
wis_downloader.egg-info/top_level.txt