Metadata-Version: 2.1
Name: wis-downloader
Version: 0.3.5
Summary: A downloader for WIS
Home-page: http://124.93.160.156:18888/zhujianfeng/wis-downloader
Author: Jeff Zhu
Author-email: zjf014@gmail.com
License: MIT license
Keywords: wis_downloader
Platform: UNKNOWN
Classifier: Development Status :: 2 - Pre-Alpha
Classifier: Intended Audience :: Developers
Classifier: License :: OSI Approved :: MIT License
Classifier: Natural Language :: English
Classifier: Programming Language :: Python :: 3
Classifier: Programming Language :: Python :: 3.7
Classifier: Programming Language :: Python :: 3.8
Classifier: Programming Language :: Python :: 3.9
Requires-Python: >=3.7
License-File: LICENSE
